{"Exif":{"Lat":0,"Long":0,"Date":"2022-01-07T23:57:14-08:00","Tags":{"BrightnessValue":0.321875,"ComponentsConfiguration":"","CompressedBitsPerPixel":2,"Copyright":"Copyright 2022. All rights reserved.","CustomRendered|int":"1","DateTimeDigitized|time.Time":"2022-01-07T23:57:14-08:00","DateTimeOriginal|time.Time":"2022-01-07T23:57:14-08:00","DateTime|time.Time":"2022-01-08T00:01:31-08:00","DigitalZoomRatio|*big.Rat":"1","ExposureTime|*big.Rat":"1/160","FNumber":2,"FileSource":"","FocalLength":50,"FocalLengthIn35mmFilm|int":"50","ISOSpeedRatings|int":"1600","ImageDescription":"                                Processed with VSCO with kp4 preset","LensModel":"FE 50mm F1.8","LightSource|int":"0","Make":"SONY","MaxApertureValue":1.6953125,"Model":"ILCE-7M2","Orientation|int":"1","PixelXDimension|int":"1080","PixelYDimension|int":"1447","SceneCaptureType|int":"0","SceneType":"","Software":"VSCO","UserComment":"ASCII{\"key\":\"kp4\"}"}}}
